multireq/Proxy.py
multireq/__init__.py
multireq/multiRequester.py
multireq/proxyManager.py
multireq/useragentManager.py
multireq/useragents.txt
multireq-0.0.10.dist-info/METADATA
multireq-0.0.10.dist-info/RECORD
multireq-0.0.10.dist-info/WHEEL
multireq-0.0.10.dist-info/top_level.txt
