Metadata-Version: 2.1
Name: multireq
Version: 0.0.10
Summary: Package for sending multi requests with different proxies.
Home-page: https://github.com/rafet/multi-requester
Author: rafet
License: MIT
Platform: UNKNOWN
Classifier: License :: OSI Approved :: MIT License
Classifier: Programming Language :: Python :: 3
Classifier: Programming Language :: Python :: 3.7
Classifier: Operating System :: OS Independent
Requires-Dist: requests
